{
  "last_updated": "06-06-2026 08:07 PM",
  "count": 0,
  "items": {
    "date": "06 June 2026",
    "briefing": "Phishing attacks are becoming more sophisticated and harder to spot, with AI now being used to craft convincing fake emails at scale \u2014 making it easier for scammers to target staff at organisations like ours. Separately, a China-linked hacking group known as TA4922 has been expanding its cybercrime activity globally, which may increase risk for Australian organisations. Google has also rolled out a new feature on Android phones that can detect suspicious calls, which is worth enabling if you use an Android device.\n\n**Practical tip:** If an email or call feels urgent or unusual \u2014 even if it looks legitimate \u2014 pause and verify through a separate channel before clicking links or sharing information.",
    "generated": "06-06-2026 08:07 PM",
    "featured": {
      "title": "Google rolls out fake call detection on Android phones",
      "link": "https://securitybrief.com.au/story/google-rolls-out-fake-call-detection-on-android-phones",
      "source": "Security Brief Australia",
      "date": "05-06-2026 06:49 PM",
      "quote": "Fake call detection addresses widespread phone scam threat affecting Australian mobile users directly."
    }
  }
}